pairadigm/__init__.py
pairadigm/core.py
pairadigm/model.py
pairadigm/py.typed
pairadigm-0.5.1.dist-info/licenses/LICENSE
pairadigm-0.5.1.dist-info/METADATA
pairadigm-0.5.1.dist-info/WHEEL
pairadigm-0.5.1.dist-info/top_level.txt
pairadigm-0.5.1.dist-info/RECORD
