Metadata-Version: 2.4
Name: pairadigm
Version: 0.5.1
Summary: Concept-Guided Chain-of-Thought (CGCoT) pairwise annotation using Large Language Models
Home-page: https://github.com/mlchrzan/pairadigm
Author: Michael Leon Chrzan
Author-email: Michael Leon Chrzan <mlchrzan1@gmail.com>
License: Apache-2.0
Project-URL: Homepage, https://github.com/mlchrzan/pairadigm
Project-URL: Bug Reports, https://github.com/mlchrzan/pairadigm/issues
Project-URL: Source, https://github.com/mlchrzan/pairadigm
Keywords: nlp,annotation,pairwise-comparison,llm,machine-learning,text-analysis
Classifier: Development Status :: 4 - Beta
Classifier: Intended Audience :: Science/Research
Classifier: Intended Audience :: Developers
Classifier: Topic :: Scientific/Engineering :: Artificial Intelligence
Classifier: Topic :: Text Processing :: Linguistic
Classifier: License :: OSI Approved :: Apache Software License
Classifier: Programming Language :: Python :: 3
Classifier: Programming Language :: Python :: 3.8
Classifier: Programming Language :: Python :: 3.9
Classifier: Programming Language :: Python :: 3.10
Classifier: Programming Language :: Python :: 3.11
Classifier: Programming Language :: Python :: 3.12
Requires-Python: >=3.8
License-File: LICENSE
Requires-Dist: pandas>=1.3.0
Requires-Dist: numpy>=1.21.0
Requires-Dist: scipy>=1.7.0
Requires-Dist: plotly>=5.0.0
Requires-Dist: networkx>=2.6.0
Requires-Dist: choix>=0.3.5
Requires-Dist: python-dotenv>=0.19.0
Requires-Dist: google-genai>=0.1.0
Requires-Dist: statsmodels>=0.13.0
Requires-Dist: scikit-learn>=1.0.0
Requires-Dist: matplotlib>=3.4.0
Requires-Dist: seaborn>=0.11.0
Requires-Dist: torch>=2.0.0
Requires-Dist: transformers>=4.30.0
Provides-Extra: openai
Requires-Dist: openai>=1.0.0; extra == "openai"
Provides-Extra: anthropic
Requires-Dist: anthropic>=0.5.0; extra == "anthropic"
Provides-Extra: all
Requires-Dist: openai>=1.0.0; extra == "all"
Requires-Dist: anthropic>=0.5.0; extra == "all"
Provides-Extra: dev
Requires-Dist: pytest>=7.0.0; extra == "dev"
Requires-Dist: pytest-cov>=3.0.0; extra == "dev"
Requires-Dist: black>=22.0.0; extra == "dev"
Requires-Dist: flake8>=4.0.0; extra == "dev"
Requires-Dist: mypy>=0.950; extra == "dev"
Dynamic: author
Dynamic: home-page
Dynamic: license-file
Dynamic: requires-python
